aiforecastts/__init__.py
aiforecastts/core.py
aiforecastts/agents/__init__.py
aiforecastts/agents/forecasting_agent.py
aiforecastts/analytics/__init__.py
aiforecastts/analytics/evaluator.py
aiforecastts/analytics/features.py
aiforecastts/analytics/processor.py
aiforecastts/models/__init__.py
aiforecastts/models/ensemble.py
aiforecastts/models/hgr.py
aiforecastts/utils/__init__.py
aiforecastts-0.3.3.dist-info/licenses/LICENSE
aiforecastts-0.3.3.dist-info/METADATA
aiforecastts-0.3.3.dist-info/WHEEL
aiforecastts-0.3.3.dist-info/top_level.txt
aiforecastts-0.3.3.dist-info/RECORD
