Metadata-Version: 2.4
Name: aiforecastts
Version: 0.3.3
Summary: Scientific AI-powered Time Series Research Library
Author-email: Tuan Anh Tran <tuanthescientist@gmail.com>
License: MIT
Project-URL: Homepage, https://github.com/tuanthescientist/aiforecastts
Project-URL: Bug Tracker, https://github.com/tuanthescientist/aiforecastts/issues
Classifier: Programming Language :: Python :: 3
Classifier: Programming Language :: Python :: 3.11
Classifier: Operating System :: OS Independent
Classifier: Development Status :: 4 - Beta
Classifier: Intended Audience :: Developers
Classifier: Intended Audience :: Science/Research
Classifier: Topic :: Scientific/Engineering
Requires-Python: >=3.11
License-File: LICENSE
Requires-Dist: pandas>=2.0
Requires-Dist: numpy>=1.24
Requires-Dist: statsmodels>=0.14
Requires-Dist: prophet>=1.1
Requires-Dist: pmdarima>=2.0
Requires-Dist: xgboost>=2.0
Requires-Dist: scikit-learn>=1.3
Requires-Dist: ta>=0.11
Requires-Dist: joblib>=1.3
Requires-Dist: google-generativeai>=0.3
Provides-Extra: dev
Requires-Dist: pytest>=7.0; extra == "dev"
Requires-Dist: black; extra == "dev"
Requires-Dist: ruff; extra == "dev"
Requires-Dist: build; extra == "dev"
Requires-Dist: twine; extra == "dev"
Dynamic: license-file
